delta/__init__.py
delta/assets.py
delta/config.py
delta/data.py
delta/model.py
delta/pipeline.py
delta/utilities.py
delta2-2.0.7.dist-info/LICENSE
delta2-2.0.7.dist-info/METADATA
delta2-2.0.7.dist-info/WHEEL
delta2-2.0.7.dist-info/top_level.txt
delta2-2.0.7.dist-info/RECORD
