Metadata-Version: 2.2
Name: delta2
Version: 2.0.7
Summary: Segments and tracks bacteria
Author-email: Jean-Baptiste Lugagne <jean-baptiste.lugagne@eng.ox.ac.uk>, Owen OConnor <ooconnor@bu.edu>, Virgile Andreani <andreani@bu.edu>
License: MIT License
Project-URL: repository, https://gitlab.com/delta-microscopy/delta
Project-URL: documentation, https://delta.readthedocs.io
Keywords: bacteria,fluorescence,microscopy
Classifier: Development Status :: 5 - Production/Stable
Classifier: Programming Language :: Python :: 3
Classifier: Programming Language :: Python :: 3 :: Only
Classifier: Programming Language :: Python :: 3.10
Classifier: Programming Language :: Python :: 3.11
Classifier: Programming Language :: Python :: 3.12
Classifier: Intended Audience :: Science/Research
Classifier: License :: OSI Approved :: MIT License
Classifier: Topic :: Scientific/Engineering :: Bio-Informatics
Classifier: Topic :: Scientific/Engineering :: Image Processing
Requires-Python: >=3.10
License-File: LICENSE
Requires-Dist: scikit-image>=0.18
Requires-Dist: tifffile>=2020
Requires-Dist: opencv-python>=4.1
Requires-Dist: tensorflow>=2.16
Requires-Dist: ffmpeg-python>=0.2
Requires-Dist: requests>=2.32
